{
  "vectors": [
    {
      "name": "sol-to-jup-direct-small",
      "poolId": "pool-sol-jup",
      "inMint": "So11111111111111111111111111111111111111112",
      "inAmount": "1000000000",
      "expected": {
        "outAmount": "82398737",
        "feeAmount": "3000000",
        "inAfterFee": "997000000",
        "impactBps": 82
      }
    },
    {
      "name": "sol-to-usdc-small",
      "poolId": "pool-sol-usdc",
      "inMint": "So11111111111111111111111111111111111111112",
      "inAmount": "500000000",
      "expected": {
        "outAmount": "114712758",
        "feeAmount": "1000000",
        "inAfterFee": "499000000",
        "impactBps": 4
      }
    }
  ]
}
